README
setup.py
gbookmark2delicious/__init__.py
gbookmark2delicious.egg-info/PKG-INFO
gbookmark2delicious.egg-info/SOURCES.txt
gbookmark2delicious.egg-info/dependency_links.txt
gbookmark2delicious.egg-info/entry_points.txt
gbookmark2delicious.egg-info/requires.txt
gbookmark2delicious.egg-info/top_level.txt