Metadata-Version: 1.0
Name: gbookmark2delicious
Version: 3.3.1
Summary: Synchronize/share your Google Bookmarks to delicious.com
Home-page: http://gbookmark2delicious.googlecode.com/
Author: Yang Zhang and Anoop Johnson
Author-email: yaaang NOSPAM at REMOVECAPS gmail
License: MIT
Keywords: google delicious bookmarks synchronization synchronize synchronizer
Platform: UNKNOWN
Classifier: Development Status :: 5 - Production/Stable
Classifier: Environment :: Console
Classifier: Intended Audience :: End Users/Desktop
Classifier: License :: OSI Approved :: MIT License
Classifier: Operating System :: OS Independent
Classifier: Programming Language :: Python
Classifier: Topic :: Internet :: WWW/HTTP
